PyTado/__init__.py
PyTado/__main__.py
PyTado/const.py
PyTado/exceptions.py
PyTado/http.py
PyTado/interface/__init__.py
PyTado/interface/api/__init__.py
PyTado/interface/api/hops_tado.py
PyTado/interface/api/my_tado.py
PyTado/interface/interface.py
PyTado/logger.py
PyTado/zone/__init__.py
PyTado/zone/hops_zone.py
PyTado/zone/my_zone.py
python_tado-0.19.1.dist-info/AUTHORS
python_tado-0.19.1.dist-info/LICENSE
python_tado-0.19.1.dist-info/METADATA
python_tado-0.19.1.dist-info/WHEEL
python_tado-0.19.1.dist-info/entry_points.txt
python_tado-0.19.1.dist-info/RECORD
