Metadata-Version: 2.3
Name: python-tado
Version: 0.19.1
Summary: PyTado from chrism0dwk, modified by w.malgadey, diplix, michaelarnauts, LenhartStephan, splifter, syssi, andersonshatch, Yippy, p0thi, Coffee2CodeNL, chiefdragon, FilBr, nikilase, albertomontesg, Moritz-Schmidt, palazzem
License: GPL-3.0-or-later
Keywords: tado
Author: Chris Jewell
Author-email: chrism0dwk@gmail.com
Requires-Python: >=3.11
Classifier: Development Status :: 4 - Beta
Classifier: Intended Audience :: Developers
Classifier: License :: OSI Approved :: GNU General Public License v3 (GPLv3)
Classifier: License :: OSI Approved :: GNU General Public License v3 or later (GPLv3+)
Classifier: Natural Language :: English
Classifier: Programming Language :: Python :: 3
Classifier: Programming Language :: Python :: 3.11
Classifier: Programming Language :: Python :: 3.12
Classifier: Programming Language :: Python :: 3.13
Classifier: Topic :: Home Automation
Provides-Extra: all
Provides-Extra: dev
Provides-Extra: lint
Provides-Extra: test
Requires-Dist: black (>=24.10) ; extra == "lint" or extra == "all"
Requires-Dist: pre-commit ; extra == "dev" or extra == "all"
Requires-Dist: pylint ; extra == "lint" or extra == "all"
Requires-Dist: pytest ; extra == "test" or extra == "all"
Requires-Dist: pytest-cov ; extra == "test" or extra == "all"
Requires-Dist: pytest-mock ; extra == "test" or extra == "all"
Requires-Dist: pytest-socket ; extra == "test" or extra == "all"
Requires-Dist: pytype ; extra == "dev" or extra == "all"
Requires-Dist: requests
Requires-Dist: responses ; extra == "test" or extra == "all"
Requires-Dist: types-requests ; extra == "dev" or extra == "all"
Project-URL: Documentation, https://wmalgadey.github.io/PyTado/
Project-URL: Homepage, https://github.com/wmalgadey/PyTado
Project-URL: Repository, https://github.com/wmalgadey/PyTado
